MANIFEST.in
README.rst
setup.py
gbdx_cloud_harness/__init__.py
gbdx_cloud_harness/__init__.pyc
gbdx_cloud_harness/controller.py
gbdx_cloud_harness/controller.pyc
gbdx_cloud_harness/workflow.py
gbdx_cloud_harness/workflow.pyc
gbdx_cloud_harness.egg-info/PKG-INFO
gbdx_cloud_harness.egg-info/SOURCES.txt
gbdx_cloud_harness.egg-info/dependency_links.txt
gbdx_cloud_harness.egg-info/entry_points.txt
gbdx_cloud_harness.egg-info/requires.txt
gbdx_cloud_harness.egg-info/top_level.txt
gbdx_cloud_harness/services/__init__.py
gbdx_cloud_harness/services/__init__.pyc
gbdx_cloud_harness/services/account_storage_service.py
gbdx_cloud_harness/services/account_storage_service.pyc
gbdx_cloud_harness/services/port_service.py
gbdx_cloud_harness/services/port_service.pyc
gbdx_cloud_harness/services/task_service.py
gbdx_cloud_harness/services/task_service.pyc
gbdx_cloud_harness/services/test/__init__.py
gbdx_cloud_harness/services/test/__init__.pyc
gbdx_cloud_harness/services/test/test_acct_storage_service.py
gbdx_cloud_harness/services/test/test_port_service.py
gbdx_cloud_harness/services/test/test_task_service.py
gbdx_cloud_harness/services/test/__pycache__/test_acct_storage_service.cpython-27-PYTEST.pyc
gbdx_cloud_harness/services/test/__pycache__/test_port_service.cpython-27-PYTEST.pyc
gbdx_cloud_harness/services/test/__pycache__/test_task_service.cpython-27-PYTEST.pyc
gbdx_cloud_harness/services/test/input/README.md
gbdx_cloud_harness/services/test/input/app.py
gbdx_cloud_harness/services/test/input/data/readme.txt
gbdx_cloud_harness/services/test/input/data/subsub/test.rst
gbdx_cloud_harness/services/test/input/imgs/tester.png
gbdx_cloud_harness/services/test/vcr_cassettes/task_service.yaml
gbdx_cloud_harness/templates/task_template.py
gbdx_cloud_harness/test/__init__.py
gbdx_cloud_harness/test/__init__.pyc
gbdx_cloud_harness/test/auth_mock.py
gbdx_cloud_harness/test/auth_mock.pyc
gbdx_cloud_harness/test/conftest.py
gbdx_cloud_harness/test/test_controller.py
gbdx_cloud_harness/test/test_valid_wf.json
gbdx_cloud_harness/test/test_workflow.py
gbdx_cloud_harness/test/__pycache__/conftest.cpython-27-PYTEST.pyc
gbdx_cloud_harness/test/__pycache__/test_controller.cpython-27-PYTEST.pyc
