Metadata-Version: 1.1
Name: gbdx-cloud-harness
Version: 0.2.23
Summary: GBDX Cloud Harness
Home-page: https://github.com/TDG-Platform/cloud-harness
Author: GBDX (Michael Connor)
Author-email: mike@sparkgeo.com
License: MIT
Platform: UNKNOWN
Classifier: Development Status :: 3 - Alpha
Classifier: Intended Audience :: Developers
Classifier: Programming Language :: Python :: 2.7
